ward/__init__.py
ward/cli.py
ward/core/config.py
ward/core/orchestrator.py
ward/core/session.py
ward/core/universal_wrapper.py
ward/interceptors/__init__.py
ward/interceptors/base.py
ward/interceptors/bash.py
ward/interceptors/filesystem.py
ward/mcp_servers/__init__.py
ward/mcp_servers/sandbox_server.py
ward/mcp_servers/ward_server.py
ward/sandbox/__init__.py
ward/sandbox/docker_manager.py
ward/sandbox/manager.py
ward/utils/__init__.py
ward/utils/diff.py
ward/utils/git.py
ward/utils/metrics.py
ward/validators/base.py
ward/validators/validators.py
ward_ai-0.1.0.dist-info/licenses/LICENSE
ward_ai-0.1.0.dist-info/METADATA
ward_ai-0.1.0.dist-info/WHEEL
ward_ai-0.1.0.dist-info/entry_points.txt
ward_ai-0.1.0.dist-info/top_level.txt
ward_ai-0.1.0.dist-info/RECORD
