Metadata-Version: 2.4
Name: ward-ai
Version: 0.1.0
Summary: Ward - The Universal Safety Layer for AI Agents. Cross-platform sandbox protection for any AI agent.
Author-email: Nashih Amin <nashihamm@outlook.com>
License: MIT
Project-URL: Homepage, https://github.com/nashihamm/ward
Project-URL: Documentation, https://github.com/nashihamm/ward#readme
Project-URL: Repository, https://github.com/nashihamm/ward
Project-URL: Issues, https://github.com/nashihamm/ward/issues
Keywords: ai,sandbox,ward,safety,universal,windows,docker,claude,ollama
Classifier: Development Status :: 3 - Alpha
Classifier: Intended Audience :: Developers
Classifier: License :: OSI Approved :: MIT License
Classifier: Programming Language :: Python :: 3
Classifier: Programming Language :: Python :: 3.10
Classifier: Programming Language :: Python :: 3.11
Classifier: Programming Language :: Python :: 3.12
Classifier: Operating System :: OS Independent
Classifier: Operating System :: Microsoft :: Windows
Classifier: Operating System :: POSIX :: Linux
Classifier: Operating System :: MacOS
Requires-Python: >=3.10
License-File: LICENSE
Requires-Dist: mcp>=1.0.0
Requires-Dist: pydantic>=2.0.0
Requires-Dist: pydantic-settings>=2.0.0
Requires-Dist: aiofiles>=23.0.0
Requires-Dist: gitpython>=3.1.0
Requires-Dist: watchdog>=3.0.0
Requires-Dist: rich>=13.0.0
Requires-Dist: structlog>=23.0.0
Requires-Dist: pytest>=7.0.0
Requires-Dist: pytest-asyncio>=0.21.0
Requires-Dist: ruff>=0.1.0
Requires-Dist: click>=8.0.0
Requires-Dist: psutil>=5.9.0
Provides-Extra: dev
Requires-Dist: pytest-cov>=4.0.0; extra == "dev"
Requires-Dist: mypy>=1.0.0; extra == "dev"
Requires-Dist: black>=23.0.0; extra == "dev"
Requires-Dist: pre-commit>=3.0.0; extra == "dev"
Dynamic: license-file
